{
    "page_type": "contact_page",
    "name": "联系页面布局",
    "description": "RummyRoyal 主题联系我们页面布局",
    "version": "1.0.0",
    "inherit_regions": {
        "header": "home_page",
        "footer": "home_page"
    },
    "layout_config": {
        "header": [],
        "content": [
            {
                "code": "contact-content",
                "enabled": true,
                "instance_id": "contact-default",
                "config": {
                    "content.badge": "Contact Us",
                    "content.title": "Get in Touch",
                    "content.description": "Have questions or need assistance? Our support team is here to help you 24/7.",
                    "contact.email": "support@rummyroyal.com",
                    "contact.phone": "+91 1800-XXX-XXXX",
                    "contact.address": "RummyRoyal HQ, Bangalore, India",
                    "contact.hours": "24/7 Customer Support"
                }
            }
        ],
        "footer": []
    },
    "notes": "联系我们页面布局"
}
